actipyme/__init__.py
actipyme/_params.py
actipyme/models.py
actipyme-0.2.0.dist-info/licenses/LICENSE
actipyme-0.2.0.dist-info/METADATA
actipyme-0.2.0.dist-info/WHEEL
actipyme-0.2.0.dist-info/RECORD
